aioworldline/__init__.py
aioworldline/__main__.py
aioworldline/conf.py
aioworldline/worldline.py
aioworldline-0.4.3.dist-info/licenses/AUTHORS.rst
aioworldline-0.4.3.dist-info/licenses/LICENSE
aioworldline-0.4.3.dist-info/METADATA
aioworldline-0.4.3.dist-info/WHEEL
aioworldline-0.4.3.dist-info/top_level.txt
aioworldline-0.4.3.dist-info/RECORD
