Metadata-Version: 2.4
Name: aioworldline
Version: 0.4.3
Summary: Unofficial Worldline portal data retrieving client
Author-email: Oleg Korsak <kamikaze.is.waiting.you@gmail.com>
License-Expression: GPL-3.0
Project-URL: Homepage, https://github.com/kamikaze/aioworldline
Project-URL: Documentation, https://github.com/kamikaze/aioworldline/wiki
Classifier: Development Status :: 4 - Beta
Classifier: Programming Language :: Python
Requires-Python: <3.15.0,>=3.13.9
License-File: LICENSE
License-File: AUTHORS.rst
Requires-Dist: aiohttp[speedups]~=3.13.2
Requires-Dist: pydantic~=2.12.4
Requires-Dist: pydantic-settings~=2.12.0
Dynamic: license-file
